jaxloudnorm/__init__.py
jaxloudnorm/iirfilter.py
jaxloudnorm/lfilter.py
jaxloudnorm/meter.py
jaxloudnorm/normalize.py
jaxloudnorm/util.py
jaxloudnorm-0.3.0.dist-info/licenses/LICENSE
jaxloudnorm-0.3.0.dist-info/METADATA
jaxloudnorm-0.3.0.dist-info/WHEEL
jaxloudnorm-0.3.0.dist-info/top_level.txt
jaxloudnorm-0.3.0.dist-info/RECORD
