Metadata-Version: 2.4
Name: jaxloudnorm
Version: 0.3.0
Summary: Implementation of ITU-R BS.1770-4 loudness algorithm in JAX
Author-email: David Braun <braun@ccrma.stanford.edu>, Boris Kuznetsov <boris.kuznetsov@mailbox.org>, Christian Steinmetz <c.j.steinmetz@qmul.ac.uk>
License-Expression: MIT
Project-URL: Homepage, https://github.com/DBraun/jaxloudnorm
Project-URL: Repository, https://github.com/DBraun/jaxloudnorm
Project-URL: Bug Tracker, https://github.com/DBraun/jaxloudnorm/issues
Classifier: Programming Language :: Python :: 3
Classifier: Programming Language :: Python :: 3.9
Classifier: Programming Language :: Python :: 3.10
Classifier: Programming Language :: Python :: 3.11
Classifier: Programming Language :: Python :: 3.12
Classifier: Operating System :: OS Independent
Classifier: Topic :: Multimedia :: Sound/Audio
Classifier: Topic :: Scientific/Engineering
Requires-Python: >=3.9
License-File: LICENSE
Requires-Dist: jax>=0.4.13
Requires-Dist: jaxtyping>=0.2.20
Requires-Dist: numpy>=1.21.0
Requires-Dist: scipy>=1.7.0
Requires-Dist: pysoundfile>=0.9.0
Provides-Extra: test
Requires-Dist: pytest>=7.0; extra == "test"
Provides-Extra: docs
Requires-Dist: sphinx>=8.0; extra == "docs"
Requires-Dist: sphinx-rtd-theme>=3.0; extra == "docs"
Requires-Dist: sphinx-autodoc-typehints>=3.0; extra == "docs"
Dynamic: license-file
